includebeeredgeth/__main__.py
include_beer_edge_th-0.3.0.dist-info/LICENSE
include_beer_edge_th-0.3.0.dist-info/METADATA
include_beer_edge_th-0.3.0.dist-info/WHEEL
include_beer_edge_th-0.3.0.dist-info/top_level.txt
include_beer_edge_th-0.3.0.dist-info/RECORD
