Metadata-Version: 2.1
Name: include-beer-edge-th
Version: 0.3.0
Summary: Monitor temperature and humidity on edge device
Home-page: https://github.com/mbhein/include-beer-edge-th
Author: Matthew Hein
Author-email: matthew.hein@gmail.com
License: MIT
Platform: UNKNOWN
Classifier: License :: OSI Approved :: MIT License
Classifier: Programming Language :: Python :: 3
Classifier: Programming Language :: Python :: 3.6
Classifier: Programming Language :: Python :: 3.7
Classifier: Programming Language :: Python :: 3.8
Requires-Dist: include-beer-DHT11
Requires-Dist: include-beer-core
